pytranspose/__init__.py
pytranspose/transpose.py
pytranspose-0.0.2.dist-info/DESCRIPTION.rst
pytranspose-0.0.2.dist-info/METADATA
pytranspose-0.0.2.dist-info/RECORD
pytranspose-0.0.2.dist-info/WHEEL
pytranspose-0.0.2.dist-info/metadata.json
pytranspose-0.0.2.dist-info/top_level.txt
