Metadata-Version: 2.0
Name: pytranspose
Version: 0.0.2
Summary: transpose nested dict and list.
Home-page: https://github.com/kktk-KO/pytranspose
Author: kktk
Author-email: kktkko3579@gmail.com
License: CC0
Keywords: python list dict transpose
Platform: UNKNOWN
Classifier: Development Status :: 3 - Alpha
Classifier: Intended Audience :: Developers
Classifier: License :: CC0 1.0 Universal (CC0 1.0) Public Domain Dedication
Classifier: Programming Language :: Python :: 2
Classifier: Programming Language :: Python :: 3
